dynamic_raw_id/__init__.py
dynamic_raw_id/admin.py
dynamic_raw_id/filters.py
dynamic_raw_id/static/dynamic_raw_id/js/dynamic_raw_id.js
dynamic_raw_id/templates/dynamic_raw_id/admin/filters/dynamic_raw_id_filter.html
dynamic_raw_id/templates/dynamic_raw_id/admin/widgets/dynamic_raw_id_field.html
dynamic_raw_id/templates/dynamic_raw_id/label.html
dynamic_raw_id/templates/dynamic_raw_id/multi_label.html
dynamic_raw_id/tests/__init__.py
dynamic_raw_id/tests/conftest.py
dynamic_raw_id/tests/test_admin.py
dynamic_raw_id/tests/test_admin_changelist.py
dynamic_raw_id/tests/test_admin_inlines.py
dynamic_raw_id/tests/test_django_admin.py
dynamic_raw_id/tests/test_integrity.py
dynamic_raw_id/tests/testapp/__init__.py
dynamic_raw_id/tests/testapp/admin.py
dynamic_raw_id/tests/testapp/migrations/0001_initial.py
dynamic_raw_id/tests/testapp/migrations/__init__.py
dynamic_raw_id/tests/testapp/models.py
dynamic_raw_id/tests/testapp/settings.py
dynamic_raw_id/tests/testapp/urls.py
dynamic_raw_id/urls.py
dynamic_raw_id/views.py
dynamic_raw_id/widgets.py
django_dynamic_raw_id-4.3.dist-info/LICENSE
django_dynamic_raw_id-4.3.dist-info/METADATA
django_dynamic_raw_id-4.3.dist-info/WHEEL
django_dynamic_raw_id-4.3.dist-info/RECORD
