Metadata-Version: 2.1
Name: django-dynamic-raw-id
Version: 4.3
Summary: raw_id_fields widget replacement that handles display of an object's string value on change.
Home-page: https://github.com/lincolnloop/django-dynamic-raw-id
License: MIT
Keywords: django,widget,field,admin,raw-id,foreignkey
Author: Martin Mahner
Requires-Python: >=3.8,<4.0
Classifier: Development Status :: 5 - Production/Stable
Classifier: Environment :: Web Environment
Classifier: Framework :: Django
Classifier: Intended Audience :: Developers
Classifier: License :: OSI Approved :: MIT License
Classifier: Operating System :: OS Independent
Classifier: Programming Language :: Python
Classifier: Programming Language :: Python :: 3
Classifier: Programming Language :: Python :: 3.8
Classifier: Programming Language :: Python :: 3.9
Classifier: Programming Language :: Python :: 3.10
Classifier: Programming Language :: Python :: 3.11
Classifier: Programming Language :: Python :: 3.12
Requires-Dist: django (>=3.2)
Project-URL: Bugtracker, https://github.com/lincolnloop/django-dynamic-raw-id/issues
Project-URL: Source, https://github.com/lincolnloop/django-dynamic-raw-id
